publica_utils/__init__.py
publica_utils/main.py
publica_utils/test_main.py
publica_utils-0.1.1.dist-info/METADATA
publica_utils-0.1.1.dist-info/WHEEL
publica_utils-0.1.1.dist-info/entry_points.txt
publica_utils-0.1.1.dist-info/RECORD
