Metadata-Version: 2.1
Name: publica_utils
Version: 0.1.1
Summary: A tool to help publica engineer
Author: dimitri
Author-email: dimitriwyzlic@gmail.com
Requires-Python: >=3.9,<4.0
Classifier: Programming Language :: Python :: 3
Classifier: Programming Language :: Python :: 3.9
Classifier: Programming Language :: Python :: 3.10
Classifier: Programming Language :: Python :: 3.11
Classifier: Programming Language :: Python :: 3.12
Requires-Dist: shellpy (>=0.5.1,<0.6.0)
